npm2rez/__init__.py
npm2rez/__main__.py
npm2rez/cli.py
npm2rez/core.py
npm2rez-0.3.0.dist-info/LICENSE
npm2rez-0.3.0.dist-info/METADATA
npm2rez-0.3.0.dist-info/WHEEL
npm2rez-0.3.0.dist-info/entry_points.txt
npm2rez-0.3.0.dist-info/RECORD
