Metadata-Version: 2.1
Name: npm2rez
Version: 0.3.0
Summary: Convert npm packages to rez packages
Author: longhao
Author-email: hal.long@outlook.com
Requires-Python: >=3.8,<4.0
Classifier: Programming Language :: Python :: 3
Classifier: Programming Language :: Python :: 3.8
Classifier: Programming Language :: Python :: 3.9
Classifier: Programming Language :: Python :: 3.10
Classifier: Programming Language :: Python :: 3.11
Classifier: Programming Language :: Python :: 3.12
Classifier: Programming Language :: Python :: 3.13
Requires-Dist: click (>=8.1.8,<9.0.0)
Project-URL: Homepage, https://github.com/loonghao/npm2rez
Project-URL: Issues, https://github.com/loonghao/npm2rez/issues
